odoo/addons/l10n_it_ricevute_bancarie/README.rst
odoo/addons/l10n_it_ricevute_bancarie/__init__.py
odoo/addons/l10n_it_ricevute_bancarie/__manifest__.py
odoo/addons/l10n_it_ricevute_bancarie/data/riba_sequence.xml
odoo/addons/l10n_it_ricevute_bancarie/demo/riba_demo.xml
odoo/addons/l10n_it_ricevute_bancarie/i18n/it.po
odoo/addons/l10n_it_ricevute_bancarie/i18n/l10n_it_ricevute_bancarie.pot
odoo/addons/l10n_it_ricevute_bancarie/migrations/13.0.1.0.0/pre-migration.py
odoo/addons/l10n_it_ricevute_bancarie/migrations/14.0.1.0.1/post-migration.py
odoo/addons/l10n_it_ricevute_bancarie/migrations/14.0.1.8.2/noupdate_changes.xml
odoo/addons/l10n_it_ricevute_bancarie/migrations/14.0.1.8.2/post-migration.py
odoo/addons/l10n_it_ricevute_bancarie/models/__init__.py
odoo/addons/l10n_it_ricevute_bancarie/models/account.py
odoo/addons/l10n_it_ricevute_bancarie/models/account_config.py
odoo/addons/l10n_it_ricevute_bancarie/models/bank_statement.py
odoo/addons/l10n_it_ricevute_bancarie/models/ir_ui_menu.py
odoo/addons/l10n_it_ricevute_bancarie/models/partner.py
odoo/addons/l10n_it_ricevute_bancarie/models/riba.py
odoo/addons/l10n_it_ricevute_bancarie/models/riba_config.py
odoo/addons/l10n_it_ricevute_bancarie/readme/CONFIGURE.rst
odoo/addons/l10n_it_ricevute_bancarie/readme/CONTRIBUTORS.rst
odoo/addons/l10n_it_ricevute_bancarie/readme/DESCRIPTION.rst
odoo/addons/l10n_it_ricevute_bancarie/readme/ROADMAP.rst
odoo/addons/l10n_it_ricevute_bancarie/readme/USAGE.rst
odoo/addons/l10n_it_ricevute_bancarie/report/__init__.py
odoo/addons/l10n_it_ricevute_bancarie/report/distinta_qweb.py
odoo/addons/l10n_it_ricevute_bancarie/report/report.xml
odoo/addons/l10n_it_ricevute_bancarie/security/ir.model.access.csv
odoo/addons/l10n_it_ricevute_bancarie/security/riba_security.xml
odoo/addons/l10n_it_ricevute_bancarie/static/description/icon.png
odoo/addons/l10n_it_ricevute_bancarie/static/description/index.html
odoo/addons/l10n_it_ricevute_bancarie/tests/__init__.py
odoo14_addon_l10n_it_ricevute_bancarie-14.0.1.20.2.dist-info/METADATA
odoo14_addon_l10n_it_ricevute_bancarie-14.0.1.20.2.dist-info/WHEEL
odoo14_addon_l10n_it_ricevute_bancarie-14.0.1.20.2.dist-info/top_level.txt
odoo14_addon_l10n_it_ricevute_bancarie-14.0.1.20.2.dist-info/RECORD
