Metadata-Version: 2.1
Name: odoo14-addon-l10n_it_ricevute_bancarie
Version: 14.0.1.20.2
Summary: Ricevute bancarie
Home-page: https://github.com/OCA/l10n-italy
Author: Odoo Community Association (OCA)
Author-email: support@odoo-community.org
License: AGPL-3
Classifier: Programming Language :: Python
Classifier: Framework :: Odoo
Classifier: Framework :: Odoo :: 14.0
Classifier: License :: OSI Approved :: GNU Affero General Public License v3
Classifier: Development Status :: 4 - Beta
Requires-Python: >=3.6
Requires-Dist: odoo14-addon-account-due-list
Requires-Dist: odoo14-addon-l10n-it-abicab
Requires-Dist: odoo14-addon-l10n-it-fatturapa-out
Requires-Dist: odoo14-addon-l10n-it-fiscalcode
Requires-Dist: odoo<14.1dev,>=14.0a
